jupyter_interpreter_mcp/__init__.py
jupyter_interpreter_mcp/__main__.py
jupyter_interpreter_mcp/notebook.py
jupyter_interpreter_mcp/py.typed
jupyter_interpreter_mcp/remote.py
jupyter_interpreter_mcp/server.py
jupyter_interpreter_mcp-0.2.1.dist-info/licenses/LICENSE
jupyter_interpreter_mcp-0.2.1.dist-info/METADATA
jupyter_interpreter_mcp-0.2.1.dist-info/WHEEL
jupyter_interpreter_mcp-0.2.1.dist-info/entry_points.txt
jupyter_interpreter_mcp-0.2.1.dist-info/top_level.txt
jupyter_interpreter_mcp-0.2.1.dist-info/RECORD
