Metadata-Version: 2.4
Name: jupyter-interpreter-mcp
Version: 0.2.1
Summary: A Jupyter-based MCP server for code interpretation
Author: Leopold Seidler
License: MIT
Requires-Python: >=3.10
License-File: LICENSE
Requires-Dist: mcp>=1.0.0
Requires-Dist: ipykernel>=7.0.0
Requires-Dist: python-dotenv>=1.0.0
Requires-Dist: requests>=2.31.0
Requires-Dist: websockets>=12.0
Provides-Extra: dev
Requires-Dist: pre-commit>=3.6.0; extra == "dev"
Requires-Dist: black>=24.1.0; extra == "dev"
Requires-Dist: ruff>=0.1.0; extra == "dev"
Requires-Dist: mypy>=1.8.0; extra == "dev"
Requires-Dist: pyupgrade>=3.15.0; extra == "dev"
Requires-Dist: types-requests>=2.31.0; extra == "dev"
Requires-Dist: tox>=4.0; extra == "dev"
Provides-Extra: test
Requires-Dist: pytest>=7.0.0; extra == "test"
Requires-Dist: pytest-cov>=4.0.0; extra == "test"
Requires-Dist: pytest-asyncio>=0.21.0; extra == "test"
Requires-Dist: pytest-mock>=3.10.0; extra == "test"
Requires-Dist: testcontainers>=3.7.0; extra == "test"
Dynamic: license-file
